ebj2/__init__.py
ebj2/coder.py
ebj2-0.0.1.dist-info/METADATA
ebj2-0.0.1.dist-info/WHEEL
ebj2-0.0.1.dist-info/top_level.txt
ebj2-0.0.1.dist-info/RECORD
