Metadata-Version: 2.1
Name: ebj2
Version: 0.0.1
Summary: Embedded Binary JSON
Home-page: https://gitlab.com/urain39/ebj2
Author: urain39
Author-email: urain39@qq.com
License: MIT
Keywords: json,binary-json,embedded
Platform: all
Classifier: Development Status :: 4 - Beta
Classifier: Operating System :: OS Independent
Classifier: Intended Audience :: Developers
Classifier: License :: OSI Approved :: BSD License
Classifier: Programming Language :: Python
Classifier: Programming Language :: Python :: Implementation
Classifier: Programming Language :: Python :: 3
Classifier: Programming Language :: Python :: 3.4
Classifier: Programming Language :: Python :: 3.5
Classifier: Programming Language :: Python :: 3.6
Classifier: Topic :: Software Development :: Libraries
